book_manager/__init__.py
book_manager/apps.py
book_manager/forms.py
book_manager/importers.py
book_manager/models.py
book_manager/types.py
book_manager/urls.py
book_manager/validators.py
book_manager/views.py
book_manager/wildewidgets.py
book_manager/management/__init__.py
book_manager/management/commands/__init__.py
book_manager/management/commands/import_csv.py
book_manager/migrations/0001_initial.py
book_manager/migrations/0002_bookauthor_ordering.py
book_manager/migrations/0003_model_ordering.py
book_manager/migrations/__init__.py
django_book_manager-0.3.2.dist-info/LICENSE.txt
django_book_manager-0.3.2.dist-info/METADATA
django_book_manager-0.3.2.dist-info/WHEEL
django_book_manager-0.3.2.dist-info/top_level.txt
django_book_manager-0.3.2.dist-info/RECORD
