Metadata-Version: 2.1
Name: django-book-manager
Version: 0.3.2
Summary: Reusable Django app for managing lists of books with ratings.
Home-page: https://github.com/caltechads/django-book-manager
Author: Caltech IMSS ADS
Author-email: cmalek@caltech.edu
Keywords: django
Classifier: Development Status :: 4 - Beta
Classifier: Environment :: Console
Classifier: Intended Audience :: Developers
Classifier: Operating System :: OS Independent
Classifier: Programming Language :: Python
Classifier: Programming Language :: Python :: 3
Classifier: Programming Language :: Python :: 3.7
Classifier: Programming Language :: Python :: 3.8
Classifier: Programming Language :: Python :: 3.9
Classifier: Programming Language :: Python :: 3.10
Classifier: Topic :: Software Development :: Testing
License-File: LICENSE.txt
Requires-Dist: django-extensions
Requires-Dist: nameparser
